cue/__init__.py
cue/_block.py
cue/_context.py
cue/_errors.py
cue/_executable.py
cue/_pipeline.py
cue/_pipes.py
cue/_script.py
cue/cli.py
cue/orchestrator.py
cue/run_handler.py
py_cue-0.1.0.dist-info/LICENSE
py_cue-0.1.0.dist-info/METADATA
py_cue-0.1.0.dist-info/WHEEL
py_cue-0.1.0.dist-info/entry_points.txt
py_cue-0.1.0.dist-info/top_level.txt
py_cue-0.1.0.dist-info/RECORD
