Metadata-Version: 2.1
Name: py-cue
Version: 0.1.0
Summary: Cue: Script Orchestration for Data Analysis
Home-page: UNKNOWN
Author: ktvng
License: MIT
Project-URL: Source Code, https://github.com/ktvng/cue
Platform: UNKNOWN
Requires-Python: >=3.8
Requires-Dist: pyyaml (>=5.2)
